tglogging/__init__.py
tglogging/tglogger.py
tglogging-0.0.4.dist-info/LICENSE
tglogging-0.0.4.dist-info/METADATA
tglogging-0.0.4.dist-info/WHEEL
tglogging-0.0.4.dist-info/top_level.txt
tglogging-0.0.4.dist-info/RECORD
