Metadata-Version: 2.1
Name: tglogging
Version: 0.0.4
Summary: A python package to stream your app logs to a telegram chat in realtime.
Home-page: https://github.com/subinps/tglogging
Author: subinps
License: MIT
Project-URL: Tracker, https://github.com/subinps/tglogging/issues
Project-URL: Source, https://github.com/subinps/tglogging
Platform: UNKNOWN
Classifier: Programming Language :: Python :: 3
Classifier: License :: OSI Approved :: MIT License
Classifier: Operating System :: OS Independent
Requires-Python: >=3.6
License-File: LICENSE
Requires-Dist: aiohttp
Requires-Dist: nest-asyncio
